README.md
setup.py
tom_the_bomb/__init__.py
tom_the_bomb/bombs_the_tom.py
tom_the_bomb.egg-info/PKG-INFO
tom_the_bomb.egg-info/SOURCES.txt
tom_the_bomb.egg-info/dependency_links.txt
tom_the_bomb.egg-info/top_level.txt