Metadata-Version: 2.1
Name: tom-the-bomb
Version: 2039845.245908.234598
Summary: the bomb the tom the bomb tom the bomb the bomb the tom
Home-page: https://github.com/jay3332/tom-the-bomb
License: MIT
Project-URL: Issue tracker, https://github.com/jay3332/tom-the-bomb/issues
Platform: UNKNOWN
Classifier: License :: OSI Approved :: MIT License
Classifier: Intended Audience :: Developers
Classifier: Natural Language :: English
Classifier: Operating System :: OS Independent
Classifier: Programming Language :: Python :: 3.7
Classifier: Programming Language :: Python :: 3.8
Classifier: Programming Language :: Python :: 3.9
Requires-Python: >=3.7.0
